mlmarketing/__init__.py
mlmarketing-0.0.1.dist-info/WHEEL
mlmarketing-0.0.1.dist-info/METADATA
mlmarketing-0.0.1.dist-info/RECORD
