Metadata-Version: 2.1
Name: mlmarketing
Version: 0.0.1
Summary: Machine Learning for Marketing
Keywords: jax machine-learning bayesian marketing
Author: Thomas Pinder
Author-email: tompinder@live.co.uk
Requires-Python: >=3.9,<4.0
Classifier: Programming Language :: Python :: 3
Classifier: Programming Language :: Python :: 3.9
Classifier: Programming Language :: Python :: 3.10
Classifier: Programming Language :: Python :: 3.11
